pg_tasks_queue/Config.py
pg_tasks_queue/CronJobTasks.py
pg_tasks_queue/Database.py
pg_tasks_queue/Kthread.py
pg_tasks_queue/Logging.py
pg_tasks_queue/Scheduler.py
pg_tasks_queue/Worker.py
pg_tasks_queue/__init__.py
pg_tasks_queue/procinfo.py
pg_task_queue-1.38.dist-info/METADATA
pg_task_queue-1.38.dist-info/WHEEL
pg_task_queue-1.38.dist-info/top_level.txt
pg_task_queue-1.38.dist-info/RECORD
