Metadata-Version: 2.1
Name: pg-task-queue
Version: 1.38
Summary: Python asinc task system with postgres database
Home-page: https://gitlab.com/cryptoner_dev/tasks_system
Author: Alex V. Smith
Author-email: smith.it.interface@gmail.com
License: BSD
Platform: UNKNOWN
Classifier: Development Status :: 3 - Alpha
Classifier: License :: OSI Approved :: BSD License
Classifier: Operating System :: OS Independent
Classifier: Programming Language :: Python
Requires-Dist: psycopg2
Requires-Dist: pandas
Requires-Dist: sqlalchemy
Requires-Dist: sqlalchemy-utils
Requires-Dist: croniter
Requires-Dist: sentry-sdk
